{
    "sprite": {
          "file" : [
            "p_Sprite_0.png",
            "p_Sprite_1.png",
            "p_Sprite_2.png",
            "p_Sprite_3.png",
            "p_Sprite_4.png",
            "p_Sprite_5.png",
            "p_Sprite_6.png",
            "p_Sprite_7.png",
            "p_Sprite_8.png",
            "p_Sprite_9.png",
            "p_Sprite_10.png",
            "p_Sprite_11.png",
            "p_Sprite_12.png",
            "p_Sprite_13.png",
            "p_Sprite_14.png"
          ],
          "typeImage" : "frames",
          "type" : "animation",
          "duration" : 0.1,
          "looped" : true,
          "scale" : 0.25,
          "rotation" : 0
    },
    "parameters": {
        "resistance" : 0.0,
        "rotateSpeed" : 0.0,
        "thrust" : 0,
        "bonus" : 10,
        "live" : 7
    }
}